LICENSE
MANIFEST.in
README.md
requirements.txt
setup.cfg
setup.py
docs/README.rst
docs/api.rst
docs/conf.py
docs/index.rst
sniputils.egg-info/PKG-INFO
sniputils.egg-info/SOURCES.txt
sniputils.egg-info/dependency_links.txt
sniputils.egg-info/requires.txt
sniputils.egg-info/top_level.txt
src/__init__.py
src/bucket/__init__.py
src/cli/__init__.py
src/cli/cli_gen.py
src/cli/click_helper.py
src/concurrent/__init__.py
src/concurrent/parallel.py
src/conffor/__init__.py
src/conffor/conffor.py
src/conffor/csvtor.py
src/daemon/__init__.py
src/database/__init__.py
src/database/dataset.py
src/database/elastic.py
src/database/log4mongo.py
src/database/mongo.py
src/import_hook/__init__.py
src/import_hook/import_track/__init__.py
src/import_hook/reimportable/__init__.py
src/import_hook/reimportable/reable.py
src/import_hook/upstream/__init__.py
src/import_hook/upstream/track_inject.py
src/logsetting/__init__.py
src/snippets/__init__.py