Metadata-Version: 1.2
Name: sniputils
Version: 0.1.14
Summary: utils snippets for zthxxx
Home-page: https://github.com/zthxxx/sniputils
Author: zthxxx
Author-email: zthxxx.me@gmail.com
License: MIT
Platform: UNKNOWN
Requires-Python: >=2.7
